{
  "project_info": {
    "project_number": "755289313601",
    "project_id": "chat-me-fb967",
    "storage_bucket": "chat-me-fb967.appspot.com"
  },
  "client": [
    {
      "client_info": {
        "mobilesdk_app_id": "1:755289313601:android:9a387a571fab27bec951c0",
        "android_client_info": {
          "package_name": "ga.gamerique.chatme"
        }
      },
      "oauth_client": [
        {
          "client_id": "755289313601-ikhbjfcupl8gp5o13ooc5hcv8qq7lf1g.apps.googleusercontent.com",
          "client_type": 3
        }
      ],
      "api_key": [
        {
          "current_key": "AIzaSyCfoGaeR4rhhbX6z9n53b9Y-uqGbar9X_4"
        }
      ],
      "services": {
        "appinvite_service": {
          "other_platform_oauth_client": [
            {
              "client_id": "755289313601-ikhbjfcupl8gp5o13ooc5hcv8qq7lf1g.apps.googleusercontent.com",
              "client_type": 3
            }
          ]
        }
      }
    }
  ],
  "configuration_version": "1"
}